mpest/__init__.py
mpest/distribution.py
mpest/mixture_distribution.py
mpest/problem.py
mpest/types.py
mpest/utils.py
mpest/em/__init__.py
mpest/em/em.py
mpest/em/breakpointers/__init__.py
mpest/em/breakpointers/param_differ_breakpointer.py
mpest/em/breakpointers/step_count_breakpointer.py
mpest/em/breakpointers/unionable_breakpointer.py
mpest/em/distribution_checkers/__init__.py
mpest/em/distribution_checkers/finite_checker.py
mpest/em/distribution_checkers/prior_probability_threshold_checker.py
mpest/em/distribution_checkers/unionable_distribution_checker.py
mpest/models/__init__.py
mpest/models/abstract_model.py
mpest/models/exponential.py
mpest/models/gaussian.py
mpest/models/weibull.py
mpest/optimizers/__init__.py
mpest/optimizers/abstract_optimizer.py
mpest/optimizers/scipy_cg.py
mpest/optimizers/scipy_cobyla.py
mpest/optimizers/scipy_nelder_mead.py
mpest/optimizers/scipy_newton_cg.py
mpest/optimizers/scipy_slsqp.py
mpest/optimizers/scipy_tnc.py
mpest-0.1.0.dist-info/LICENSE
mpest-0.1.0.dist-info/METADATA
mpest-0.1.0.dist-info/WHEEL
mpest-0.1.0.dist-info/top_level.txt
mpest-0.1.0.dist-info/RECORD
