Metadata-Version: 2.1
Name: mpest
Version: 0.1.0
Summary: Parameter estimation of mixture distribution problem solver, based on EM algorithm
Author-email: ToxaKaz <anton.a.kazancev@gmail.com>
License: MIT License
Project-URL: Homepage, https://github.com/toxakaz/EM-algo
Keywords: EM algorithm,mixture distribution,parameter estimation
Classifier: Development Status :: 3 - Alpha
Classifier: License :: OSI Approved :: MIT License
Classifier: Programming Language :: Python
Classifier: Programming Language :: Python :: 3
Requires-Python: >=3.11
License-File: LICENSE
Requires-Dist: numpy
Requires-Dist: scipy
Provides-Extra: dev
Requires-Dist: matplotlib ; extra == 'dev'
Requires-Dist: multiprocess ; extra == 'dev'
Requires-Dist: pandas ; extra == 'dev'
Requires-Dist: pickleshare ; extra == 'dev'
Requires-Dist: pre-commit ; extra == 'dev'
Requires-Dist: pytest ; extra == 'dev'
Requires-Dist: scikit-learn ; extra == 'dev'
Requires-Dist: seaborn ; extra == 'dev'
Requires-Dist: tqdm ; extra == 'dev'
